trawa/__init__.py
trawa/tw.py
trawa-0.10.0.dist-info/METADATA
trawa-0.10.0.dist-info/WHEEL
trawa-0.10.0.dist-info/entry_points.txt
trawa-0.10.0.dist-info/top_level.txt
trawa-0.10.0.dist-info/RECORD
