Metadata-Version: 2.1
Name: trawa
Version: 0.10.0
Summary: Watch directories for transmission
Home-page: https://github.com/architek/trawa
Author: Laurent Kislaire
Author-email: teebeenator@gmail.com
License: ISC license
Keywords: transmission watch directory
Platform: UNKNOWN
Classifier: Development Status :: 5 - Production/Stable
Classifier: License :: OSI Approved :: ISC License (ISCL)
Requires-Dist: Click (>=6.0)
Requires-Dist: inotify-simple (==1.1.8)
Requires-Dist: transmissionrpc (==0.11)
Requires-Dist: PyYAML (==5.1.2)
